Metadata-Version: 2.1
Name: ccpstencil
Version: 0.8.0
Summary: An Alviss powered Template renderer where the context input can be files and entire directory structures can be rendered.
Author-email: Thordur Matthiasson <thordurm@ccpgames.com>
License: MIT License
Project-URL: Homepage, https://github.com/ccpgames/ccp-stencil
Project-URL: Documentation, https://github.com/ccpgames/ccp-stencil/blob/main/README.md
Project-URL: Repository, https://github.com/ccpgames/ccp-stencil.git
Project-URL: Issues, https://github.com/ccpgames/ccp-stencil/issues
Project-URL: Changelog, https://github.com/ccpgames/ccp-stencil/blob/main/CHANGELOG.md
Keywords: alviss,template,render,jinja2,tools,ccp,utils
Classifier: Development Status :: 3 - Alpha
Classifier: License :: OSI Approved :: MIT License
Classifier: Intended Audience :: Developers
Classifier: Programming Language :: Python
Classifier: Programming Language :: Python :: 3
Classifier: Programming Language :: Python :: 3.8
Classifier: Programming Language :: Python :: 3.9
Classifier: Programming Language :: Python :: 3.10
Classifier: Programming Language :: Python :: 3.11
Classifier: Programming Language :: Python :: 3.12
Classifier: Topic :: Software Development
Classifier: Topic :: Software Development :: Libraries
Classifier: Topic :: Software Development :: Libraries :: Python Modules
Classifier: Topic :: Utilities
License-File: LICENSE
Requires-Dist: ccptools <2,>=1.1
Requires-Dist: alviss <4,>=3.3
Requires-Dist: jinja2 <4,>=3.1
